sumchef/__init__.py
sumchef-0.1.0.dist-info/METADATA
sumchef-0.1.0.dist-info/WHEEL
sumchef-0.1.0.dist-info/RECORD
