Metadata-Version: 2.4
Name: sumchef
Version: 0.1.0
Summary: Generate maths quizzes using powerful, flexible specifications.
Project-URL: Homepage, https://github.com/robert/sumchef
Project-URL: Repository, https://github.com/robert/sumchef
Author-email: Robert Heaton <robqheaton@gmail.com.com>
Requires-Python: >=3.8
Provides-Extra: dev
Requires-Dist: pytest>=7.0.0; extra == 'dev'
